{
  "navPointKind_uncontrolled": "Uncontrolled aerodrome",
  "navPointKind_controlled": "Controlled aerodrome",
  "navPointKind_military": "Military aerodrome",
  "navPointKind_airstrip": "Airfield",
  "navPointKind_helipad": "Helipad",
  "navPointKind_vor": "VOR",
  "navPointKind_ndb": "NDB",
  "navPointKind_vor_dme": "VOR/DME",
  "navPointKind_dme": "DME",
  "navPointKind_other_airstrip": "Other airstrip",
  "navPointKind_vfr_point": "VFR point",
  "navPointKind_ifr_point": "IFR point",
  "airports": "Airports",
  "airstrips": "Airstrips",
  "otherAerodromes": "Other aerodromes",
  "loginWithFacebook": "Login with Facebook",
  "loginWithGoogle": "Login with Google",
  "aeronauticalData": "Aeronautical data",
  "windSpeed": "Wind speed",
  "windDirection": "Wind direction",
  "tas": "True airspeed",
  "vfrPoints": "VFR points",
  "settings": "Settings",
  "renameHeader": "Rename waypoint \"{name}\" to",
  "save": "Save",
  "cancel": "Cancel",
  "language": "Language",
  "countries": "Countries",
  "speedUnit": "Speed",
  "bearings": "Bearings",
  "ok": "OK",
  "airspaces": "Airspaces",
  "airspaceLabel_none": "None",
  "airspaceLabel_all": "All",
  "airspaceLabel_today": "AUP for today",
  "airspaceLabel_tomorrow": "AUP for tomorrow",
  "levels": "Altitude range",
  "hours": "Planned flight time"
}
